new_demo/__init__.py
new_demo/__main__.py
new_demo/new_demo.py
pip_demo/__init__.py
pip_demo/__main__.py
pip_demo/mysqlconnection.py
pip_demo/pip_demo.py
pip_demo-0.1.2.dist-info/DESCRIPTION.rst
pip_demo-0.1.2.dist-info/METADATA
pip_demo-0.1.2.dist-info/RECORD
pip_demo-0.1.2.dist-info/WHEEL
pip_demo-0.1.2.dist-info/entry_points.txt
pip_demo-0.1.2.dist-info/metadata.json
pip_demo-0.1.2.dist-info/top_level.txt
