Metadata-Version: 2.0
Name: pip-demo
Version: 0.1.2
Summary: Python command line html creator
Home-page: https://github.com/oscarvazquez/command_line_tool_demo
Author: Alex Quang
Author-email: im.alex.quang@gmail.com
License: UNKNOWN
